pypackageinspector/__init__.py
pypackageinspector/main.py
pypackageinspector-1.0.3.dist-info/METADATA
pypackageinspector-1.0.3.dist-info/WHEEL
pypackageinspector-1.0.3.dist-info/top_level.txt
pypackageinspector-1.0.3.dist-info/RECORD
