Metadata-Version: 2.1
Name: pypackageinspector
Version: 1.0.3
Summary: A Python package to inspect other Python packages.
Home-page: https://github.com/LpCodes/pypackageinspector
Author: https://github.com/LpCodes
Classifier: Programming Language :: Python :: 3
Classifier: License :: OSI Approved :: MIT License
Classifier: Operating System :: OS Independent
Requires-Python: >=3.6
